fakefill/__init__.py
fakefill/catchup.py
fakefill/cli.py
fakefill/helpers/__init__.py
fakefill/helpers/afutils.py
fakefill/helpers/cfutils.py
fakefill/helpers/cronvert.py
fakefill/helpers/exceptions.py
fakefill/helpers/logging.py
fakefill/helpers/sql.py
fakefill/helpers/template.py
fakefill-1.0.1.dist-info/entry_points.txt
fakefill-1.0.1.dist-info/LICENSE
fakefill-1.0.1.dist-info/WHEEL
fakefill-1.0.1.dist-info/METADATA
fakefill-1.0.1.dist-info/RECORD
