Metadata-Version: 2.1
Name: fakefill
Version: 1.0.1
Summary: Fast & Fake Backfill Airflow DAGs Status
Home-page: https://github.com/benbenbang/airflow_fakefill
License: MIT
Keywords: airflow,fakefill,backfill,fast,success,fill,migration,database
Author: Ben CHEN
Author-email: bn@benbenbang.io
Requires-Python: >=3.7,<4.0
Classifier: Development Status :: 5 - Production/Stable
Classifier: Intended Audience :: Developers
Classifier: Intended Audience :: Science/Research
Classifier: License :: OSI Approved :: MIT License
Classifier: Programming Language :: Python :: 3
Classifier: Programming Language :: Python :: 3.10
Classifier: Programming Language :: Python :: 3.6
Classifier: Programming Language :: Python :: 3.7
Classifier: Programming Language :: Python :: 3.8
Classifier: Programming Language :: Python :: 3.9
Requires-Dist: click (>=7.1.0,<8.0.0)
Requires-Dist: loguru (>=0.5.2,<0.6.0)
Requires-Dist: pyyaml (>=5.3.1,<6.0.0)
Project-URL: Repository, https://github.com/benbenbang/airflow_fakefill
